pypgdb/__init__.py
pypgdb/pgdb.py
pypgdb-1.0.0.dist-info/LICENSE
pypgdb-1.0.0.dist-info/METADATA
pypgdb-1.0.0.dist-info/WHEEL
pypgdb-1.0.0.dist-info/top_level.txt
pypgdb-1.0.0.dist-info/RECORD
