Metadata-Version: 2.1
Name: pypgdb
Version: 1.0.0
Summary: A wrapper around psycopg2
Home-page: https://github.com/nie3e/pypgdb
Author: Adrian Ćwiek
Author-email: adrcwiek@gmail.com
License: UNKNOWN
Platform: UNKNOWN
Classifier: Development Status :: 5 - Production/Stable
Classifier: Intended Audience :: Developers
Classifier: License :: OSI Approved :: MIT License
Classifier: Operating System :: OS Independent
Classifier: Programming Language :: Python :: 3.5
Classifier: Topic :: Database
Requires-Python: >=3.5
Requires-Dist: psycopg2 (>=2.8.3)
